CHANGELOG.md
poetry_plugin_dynamic_override_sources/__init__.py
poetry_plugin_dynamic_override_sources/plugins.py
poetry_plugin_dynamic_override_sources/py.typed
poetry_plugin_dynamic_override_sources-0.0.6.dist-info/LICENSE
poetry_plugin_dynamic_override_sources-0.0.6.dist-info/METADATA
poetry_plugin_dynamic_override_sources-0.0.6.dist-info/WHEEL
poetry_plugin_dynamic_override_sources-0.0.6.dist-info/entry_points.txt
poetry_plugin_dynamic_override_sources-0.0.6.dist-info/RECORD
