Metadata-Version: 2.1
Name: poetry-plugin-dynamic-override-sources
Version: 0.0.6
Summary: Poetry plugin to dynamically override sources for private mirroring
Home-page: https://github.com/burkestar/poetry-plugin-dynamic-override-sources
License: BSD-3-Clause
Keywords: packaging,poetry,pypi,pip
Author: Dustin Burke
Author-email: dustin@datarobot.com
Requires-Python: >=3.8,<4.0
Classifier: License :: OSI Approved :: BSD License
Classifier: Programming Language :: Python :: 3
Classifier: Programming Language :: Python :: 3.8
Classifier: Programming Language :: Python :: 3.9
Classifier: Programming Language :: Python :: 3.10
Classifier: Programming Language :: Python :: 3.11
Requires-Dist: poetry (>=1.6.0,<2)
Project-URL: Changelog, https://github.com/burkestar/poetry-plugin-dynamic-override-sources/blob/main/CHANGELOG.md
Project-URL: Repository, https://github.com/burkestar/poetry-plugin-dynamic-override-sources
